nettowel/__init__.py
nettowel/__main__.py
nettowel/_common.py
nettowel/cli/__init__.py
nettowel/cli/_common.py
nettowel/cli/_output.py
nettowel/cli/diff.py
nettowel/cli/help.py
nettowel/cli/ip.py
nettowel/cli/jinja.py
nettowel/cli/jsonpatch.py
nettowel/cli/logging.py
nettowel/cli/main.py
nettowel/cli/napalm.py
nettowel/cli/netmiko.py
nettowel/cli/nornir.py
nettowel/cli/pandas.py
nettowel/cli/restconf.py
nettowel/cli/scrapli.py
nettowel/cli/textfsm.py
nettowel/cli/ttp.py
nettowel/cli/yaml.py
nettowel/exceptions.py
nettowel/jinja.py
nettowel/jsonpatch.py
nettowel/logger.py
nettowel/netmiko.py
nettowel/pandas.py
nettowel/py.typed
nettowel/restconf.py
nettowel/trogon_tui.py
nettowel/ttp.py
nettowel/yaml.py
nettowel-0.6.1.dist-info/LICENSE
nettowel-0.6.1.dist-info/METADATA
nettowel-0.6.1.dist-info/WHEEL
nettowel-0.6.1.dist-info/entry_points.txt
nettowel-0.6.1.dist-info/RECORD
