Metadata-Version: 2.1
Name: nettowel
Version: 0.6.1
Summary: Network Automation Collection
Home-page: https://github.com/InfrastructureAsCode-ch/nettowel
License: Apache 2.0
Author: ubaumann
Author-email: github@m.ubaumann.ch
Requires-Python: >=3.8,<4.0
Classifier: License :: OSI Approved :: Apache Software License
Classifier: License :: Other/Proprietary License
Classifier: Programming Language :: Python :: 3
Classifier: Programming Language :: Python :: 3.8
Classifier: Programming Language :: Python :: 3.9
Classifier: Programming Language :: Python :: 3.10
Classifier: Programming Language :: Python :: 3.11
Classifier: Programming Language :: Python :: 3.12
Provides-Extra: full
Provides-Extra: jinja
Provides-Extra: jsonpatch
Provides-Extra: napalm
Provides-Extra: netmiko
Provides-Extra: nornir
Provides-Extra: pandas
Provides-Extra: scrapli
Provides-Extra: textfsm
Provides-Extra: ttp
Provides-Extra: tui
Requires-Dist: Jinja2 (>=3,<4) ; extra == "jinja" or extra == "full"
Requires-Dist: jinja2schema (>=0.1.4,<0.2.0) ; extra == "jinja" or extra == "full"
Requires-Dist: jsonpatch (>=1.33,<2.0) ; extra == "jsonpatch" or extra == "full"
Requires-Dist: napalm (>=4,<5) ; extra == "napalm" or extra == "full"
Requires-Dist: netmiko (>=4,<5) ; extra == "netmiko" or extra == "full"
Requires-Dist: nornir (>=3.2,<4.0) ; extra == "nornir" or extra == "full"
Requires-Dist: nornir-http (>=0.1,<0.2) ; extra == "nornir" or extra == "full"
Requires-Dist: nornir-jinja2 (>=0.2.0,<0.3.0) ; extra == "nornir" or extra == "full"
Requires-Dist: nornir-napalm (>=0.4,<0.5) ; extra == "nornir" or extra == "full"
Requires-Dist: nornir-netmiko (>=1.0.0,<2.0.0) ; extra == "nornir" or extra == "full"
Requires-Dist: nornir-pyxl (>=1.0.1,<2.0.0) ; extra == "nornir" or extra == "full"
Requires-Dist: nornir-rich (>=0.1,<0.2) ; extra == "nornir" or extra == "full"
Requires-Dist: nornir-scrapli (>=2023.1.30,<2024.0.0) ; extra == "nornir" or extra == "full"
Requires-Dist: nornir-utils (>=0.2.0,<0.3.0) ; extra == "nornir" or extra == "full"
Requires-Dist: pandas (>=2,<3) ; extra == "pandas" or extra == "full"
Requires-Dist: python-dotenv (>=1,<2)
Requires-Dist: qrcode (>=7.3.1,<8.0.0)
Requires-Dist: requests (>=2.27.1,<3.0.0)
Requires-Dist: rich (>=12,<14)
Requires-Dist: ruamel.yaml (>=0.18,<0.19)
Requires-Dist: scrapli (>=2023.1.30,<2024.0.0) ; extra == "scrapli" or extra == "full"
Requires-Dist: textfsm (>=1.1,<2.0) ; extra == "textfsm" or extra == "full"
Requires-Dist: trogon (>=0.5.0,<0.6.0) ; extra == "tui" or extra == "full"
Requires-Dist: ttp (>=0.9,<0.10) ; extra == "ttp" or extra == "full"
Requires-Dist: typer (>=0.9,<0.13)
Project-URL: Repository, https://github.com/InfrastructureAsCode-ch/nettowel
